neuri/__init__.py
neuri/__main__.py
neuri/gui.py
neuri/assets/Neuri_GUI_main_window.png
neuri/backend/__init__.py
neuri/backend/board_agnostic_utils.py
neuri/backend/compatible_boards.py
neuri/backend/io_manager.py
neuri/backend/parameter_validation.py
neuri/backend/signal_processing.py
neuri/backend/signal_sampling_TEMPLATE.py
neuri/backend/signal_sampling_bioamp.py
neuri/backend/signal_sampling_muse_s.py
neuri/backend/signal_sampling_neuri_lolin.py
neuri/backend/signal_sampling_neuri_v1.py
neuri/frontend/Neuri_logo.ico
neuri/frontend/Neuri_logo.png
neuri/frontend/Neuri_logo.svg
neuri/frontend/__init__.py
neuri/frontend/parameters.py
neuri/frontend/user_experience.py
neuri/frontend/widgets.py
neurigui-2.91.4.dist-info/METADATA
neurigui-2.91.4.dist-info/WHEEL
neurigui-2.91.4.dist-info/licenses/LICENSE
neurigui-2.91.4.dist-info/RECORD
