Metadata-Version: 2.4
Name: neurigui
Version: 2.91.4
Summary: NeuriGUI is a modular, cross-platform and FOSS app for exploring electrophysiological signals in real-time
Project-URL: Homepage, https://github.com/SoftcodingForYou/NeuriGUI
Project-URL: Bug Tracker, https://github.com/SoftcodingForYou/NeuriGUI/issues
Project-URL: Issues, https://github.com/SoftcodingForYou/NeuriGUI/issues
Author: David Marcel BAUM
Author-email: david.marcel.baum@gmail.com
Maintainer: SoftcodingForYou
Maintainer-email: david.marcel.baum@gmail.com
License: Copyright 2023 SoftcodingForYou
License-File: LICENSE
Keywords: DSP,digital signal processing,eeg,electrophysiology,neuroscience,real-time,visualization
Classifier: License :: OSI Approved :: BSD License
Classifier: Operating System :: OS Independent
Classifier: Programming Language :: Python :: 3
Requires-Python: >=3.9
Requires-Dist: customtkinter
Requires-Dist: numpy
Requires-Dist: oauthlib
Requires-Dist: pillow
Requires-Dist: pygithub
Requires-Dist: pylsl
Requires-Dist: pyqt5
Requires-Dist: pyqtgraph
Requires-Dist: pyserial
Requires-Dist: requests
Requires-Dist: scipy
Requires-Dist: setuptools
